textractutil/__init__.py
textractutil/advance_parser.py
textractutil/input_validator.py
textractutil/parser.py
textractutil/response_parser.py
textractutil-0.1.0.dist-info/LICENSE
textractutil-0.1.0.dist-info/METADATA
textractutil-0.1.0.dist-info/WHEEL
textractutil-0.1.0.dist-info/top_level.txt
textractutil-0.1.0.dist-info/RECORD
