Metadata-Version: 2.1
Name: textractutil
Version: 0.1.0
Summary: Python utilities for parsing AWS Textract results.
Home-page: UNKNOWN
Author: Yifan Wu
Author-email: yw693@cornell.edu
License: UNKNOWN
Platform: UNKNOWN
Classifier: Programming Language :: Python :: 3
Classifier: License :: OSI Approved :: MIT License
Classifier: Operating System :: OS Independent
Requires-Python: >=3.3
